oscardl/__init__.py
oscardl/cli.py
oscardl/download.py
oscar_corpus_downloader-0.1.0.dist-info/LICENSE
oscar_corpus_downloader-0.1.0.dist-info/METADATA
oscar_corpus_downloader-0.1.0.dist-info/WHEEL
oscar_corpus_downloader-0.1.0.dist-info/entry_points.txt
oscar_corpus_downloader-0.1.0.dist-info/RECORD
