Metadata-Version: 2.1
Name: oscar-corpus-downloader
Version: 0.1.0
Summary: OSCAR Corpus Download Tool
Home-page: https://github.com/jtourille/oscar-corpus-downloader
License: MIT
Keywords: oscar,corpus
Author: Julien Tourille
Author-email: julien.tourille@gmail.com
Requires-Python: >=3.9
Classifier: License :: OSI Approved :: MIT License
Classifier: Programming Language :: Python :: 3
Classifier: Programming Language :: Python :: 3.9
Classifier: Programming Language :: Python :: 3.10
Classifier: Programming Language :: Python :: 3.11
Classifier: Programming Language :: Python :: 3.12
Requires-Dist: beautifulsoup4 (>=4.12.2,<5.0.0)
Requires-Dist: click (>=8.1.7,<9.0.0)
Requires-Dist: joblib (>=1.3.2,<2.0.0)
Requires-Dist: loguru (>=0.7.2,<0.8.0)
Requires-Dist: requests (>=2.31.0,<3.0.0)
Requires-Dist: tqdm (>=4.66.1,<5.0.0)
Project-URL: Documentation, https://github.com/jtourille/oscar-corpus-downloader
Project-URL: Repository, https://github.com/jtourille/oscar-corpus-downloader
